suneigen4py.cp37-win32.pyd
suneigen4py-0.0.1.dist-info/LICENSE
suneigen4py-0.0.1.dist-info/METADATA
suneigen4py-0.0.1.dist-info/WHEEL
suneigen4py-0.0.1.dist-info/top_level.txt
suneigen4py-0.0.1.dist-info/RECORD
