Metadata-Version: 2.1
Name: suneigen4py
Version: 0.0.1
Summary: A C++ wrapper with a python interface to SUNDIALS.
Home-page: UNKNOWN
Author: Kristian Meyer
Author-email: km@meyerct.com
License: UNKNOWN
Platform: UNKNOWN
License-File: LICENSE
Provides-Extra: test
Requires-Dist: pytest ; extra == 'test'
